{"ambulance": 3092, "eatery": 4569, "sculptor": 4811, "have": 389, "clear": 793, "ear": 1108, "wicker": 3313, "aside": 3999, "coats": 800, "tongs": 3534, "flipped": 4000, "croquet": 4657, "fourth": 4066, "Construction": 764, "peer": 3029, "policeman": 1373, "captures": 4394, "what": 382, "pants": 128, "waterside": 4696, "human": 2161, "wrong": 4837, "As": 3093, "smelling": 3743, "apron": 512, "DJ": 2185, "herbs": 4889, "testing": 3949, "descend": 4143, "bouncing": 2053, "wire": 1348, "beyond": 3744, "messy": 1869, "about": 238, "tucked": 4590, "medical": 1508, "dryer": 2657, "middle-aged": 571, "Americans": 3443, "Times": 3006, "gown": 1636, "homeless": 1325, "long": 194, "sword": 1422, "smiling": 133, "numbered": 2477, "Yankees": 4833, "downhill": 1605, "counter": 569, "socks": 1240, "boots": 456, "hairy": 3884, "curling": 3437, "feeding": 1489, "toddler": 352, "conveyor": 3963, "storage": 3409, "Asia": 2267, "form": 1659, "cemetery": 3754, "cement": 636, "%": 4966, "leads": 1632, "stretches": 2079, "lobby": 2929, "swimwear": 3643, "pitching": 3323, "licking": 1877, "fast": 1269, "weaves": 4244, "sawing": 3133, "log": 1010, "currently": 3902, "electronic": 1581, "microscopes": 3048, "steal": 4396, "showing": 526, "how": 874, "look": 190, "formation": 1491, "Muslim": 2894, "goalie": 1097, "golden": 983, "jogger": 3660, "high-five": 4160, "scared": 4018, "laying": 297, "mobile": 1669, "earmuffs": 3371, "crest": 4023, "Singer": 4282, "cafeteria": 2802, "Asians": 2233, "squats": 2301, "South": 2944, "straw": 847, "someone": 425, "ends": 3659, "kissing": 690, "spending": 3984, "business": 675, "torches": 4328, "those": 3066, "several": 310, "or": 217, "snow": 100, "audio": 4211, "bottles": 1214, "highly": 4528, "sexy": 4477, "varying": 2959, "boy": 31, "clears": 4595, "exhibit": 1959, "clothed": 2665, "boats": 948, "balloons": 707, "mountainside": 2080, "oversized": 3741, "exit": 3431, "helicopter": 2071, "headdresses": 4546, "outdoors": 302, "Guys": 3503, "hold": 533, "kisses": 1809, "somewhat": 3214, "presses": 4081, "rickshaw": 2684, "mound": 1352, "parlor": 4535, "towing": 4904, "relaxing": 861, "mirrored": 4441, "ladders": 3196, "refreshing": 4920, "rough": 1615, "hay": 1098, "weeds": 3365, "chased": 3132, "spin": 3347, "deli": 2743, "grabbing": 1904, "pokes": 4005, "underwater": 1181, "patterned": 1561, "hot": 723, "sparkly": 4732, "stilts": 2081, "American": 436, "defensive": 3855, "Bicycle": 4376, "goofy": 4075, "poster": 1278, "cake": 706, "post": 1131, "outcropping": 4630, "Women": 513, "kilts": 3712, "bulldozer": 2082, "bite": 1939, "sport": 1091, "contents": 2658, "monitor": 2491, "posing": 264, "craft": 1750, "drop": 3401, "huddled": 2984, "ridden": 3128, "courtyard": 1347, "bookstore": 2697, "buying": 1336, "gestures": 1781, "nurse": 2462, "wrist": 3670, "alley": 677, "city": 112, "telephone": 1577, "material": 1798, "boat": 182, "Union": 4937, "ship": 1107, "mingle": 4035, "sauce": 4973, "directing": 2932, "onlookers": 596, "riot": 2809, "folded": 1776, "pie": 3354, "higher": 4599, "waters": 1157, "crystal": 3966, "blowing": 702, "pregnant": 4117, "photography": 4742, "St": 3436, "explaining": 3025, "put": 1019, "wander": 4710, "admire": 4395, "singers": 3299, "before": 607, "rusty": 3382, "kids": 246, "lane": 1200, "flat": 1971, "rustic": 3885, "wrestling": 1035, "hijab": 4897, "queen": 4862, "grills": 3067, "wavy": 4584, "from": 65, "Square": 2547, "wrapped": 955, "dropping": 3210, "tricycle": 2057, "hoodie": 869, "whilst": 941, "wiping": 2975, "routine": 1292, "lacrosse": 2058, "ditch": 3713, "trim": 2651, "skirts": 1270, "Middle-aged": 3002, "tent": 599, "call": 2240, "goes": 914, "persons": 2620, "tractor": 1088, "computers": 1307, "take": 454, "quickly": 1914, "experiment": 2762, "among": 704, "projector": 2316, "skating": 777, "photographed": 1573, "unfinished": 3049, "drags": 4366, "enjoying": 328, "jumped": 1838, "mopping": 3363, "fabric": 1101, "index": 3852, "ox": 4942, "ballgame": 4706, "lettering": 3541, "yard": 503, "interviewing": 4656, "Everyone": 4717, "save": 4703, "viewing": 1833, "bin": 2088, "column": 3167, "towel": 1186, "frying": 2773, "closes": 3489, "music": 343, "crutches": 3669, "diaper": 3587, "ballerinas": 3178, "marriage": 4442, "bats": 4631, "teenager": 1322, "atop": 893, "firing": 3934, "takes": 346, "artistic": 3662, "grin": 4017, "body": 305, "sprays": 2935, "redheaded": 1339, "repairing": 1389, "shots": 3841, "cups": 1526, "frolics": 4941, "ringing": 4627, "appearing": 3785, "chasing": 678, "kneel": 3813, "drives": 1018, "greenery": 2835, "Red": 1996, "goatee": 2903, "around": 82, "pastries": 3685, "pointed": 2540, "rising": 3639, "countryside": 2823, "chase": 1802, "carrier": 2790, "swimmers": 1795, "4": 1037, "speakers": 4608, "oncoming": 3383, "procession": 4362, "area": 171, "peddling": 4678, "pack": 1553, "i": 3886, "corridor": 3602, "dining": 1549, "cardigan": 3521, "colorful": 263, "snowball": 2211, "off-road": 4312, "grins": 3464, "toilet": 2724, "beating": 3634, "A": 3, "were": 2166, "Spectators": 2459, "keyboards": 4721, "There": 208, "stools": 3967, "paved": 1015, "liberty": 4759, "including": 918, "tourists": 1698, "comfortable": 4980, "pancake": 3715, "direct": 4767, "strollers": 2659, "cheers": 3400, "at": 17, "presumably": 4635, "potatoes": 3588, "pick": 1470, "tiles": 2922, "taste": 4496, "Light": 4682, "spikes": 4601, "paying": 2558, "blackboard": 4643, "shopping": 321, "observed": 4779, "broken": 1676, "boxing": 1271, "tires": 1830, "button-up": 3658, "puffy": 3635, "clowns": 2499, "scoops": 4740, "teen": 1774, "cheered": 4863, "leading": 1314, "chair": 237, "hung": 3330, "toy": 225, "presentation": 1024, "labeled": 2643, "gold": 600, "beam": 1242, "listens": 1806, "guide": 3042, "venue": 1885, "individuals": 910, "happily": 1251, "inflatable": 1050, "ravine": 4617, "special": 3166, "tie": 620, "lanterns": 3003, "posts": 4080, "closed": 895, "stroll": 1807, "parent": 3036, "garb": 1217, "puppies": 1862, "volleyball": 415, "begging": 4403, "who": 172, "ring": 803, "ground": 173, "stops": 1490, "rug": 1638, "fully": 3246, "pattern": 2361, "gloved": 3854, "excitedly": 3264, "match": 627, "rain": 591, "tables": 663, "cameras": 1788, "floating": 1057, "benches": 1276, "clapping": 1715, "cinder": 4511, "scoop": 4025, "icy": 2574, "pirate": 2253, "location": 2205, "garbage": 1081, "exhibition": 3645, ".": 2, "well-dressed": 3689, "part": 977, "burning": 2155, "bouquet": 1554, "barking": 3181, "rodeo": 553, "obscured": 3580, "pocket": 2783, "competes": 3472, "turned": 1453, "wash": 2202, "burgers": 4178, "waffle": 4953, "stage": 156, "otherwise": 4790, "perform": 536, "padded": 3327, "red-hair": 883, "record": 2756, "sailor": 2706, "headfirst": 3695, "style": 1236, "telling": 3445, "class": 729, "cyclist": 908, "hides": 3566, "gliding": 3129, "Passengers": 4461, "sea": 1004, "curtains": 4423, "crocodile": 4834, "unidentified": 4154, "towards": 281, "apples": 2641, "Indian": 685, "repelling": 4892, "shines": 2958, "course": 730, "emerges": 3612, "for": 54, "alligator": 4167, "shit": 3968, "winter": 482, "though": 1727, "skis": 1059, "balances": 1570, "plate": 752, "Various": 2105, "saxophones": 3728, "onlooking": 4719, "button": 1290, "zombie": 4067, "afternoon": 2529, "pad": 2760, "mallet": 3872, "similar": 1719, "attack": 3573, "sweatshirts": 3053, "flotation": 4197, "skydiving": 3100, "between": 399, "hole": 795, "pressure": 3146, "diner": 2994, "also": 919, "Beautiful": 3217, "lab": 870, "helps": 1300, "surrounds": 4708, "hoop": 1016, "trunks": 711, "posed": 3122, "pompoms": 4361, "treadmill": 2937, "everything": 4828, "jumper": 2237, "retrieve": 4450, "choppy": 4346, "been": 1343, "pinned": 3626, "glass": 413, "clay": 1699, "watering": 2825, "photographs": 1533, "elephant": 1545, "bins": 4183, "feathers": 2642, "heavy": 913, "pins": 1815, "peeks": 3590, "seagull": 3372, "Big": 3930, "unicycle": 1597, "stretched": 2247, "skimpy": 3904, "Yamaha": 4778, "photographing": 2612, "With": 2732, "squirted": 4464, "Baseball": 2232, "costume": 393, "propped": 2784, "painter": 3031, "coloring": 1763, "bottled": 3993, "eyed": 3946, "blazer": 2375, "runs": 204, "street": 36, "straps": 3663, "An": 55, "different": 590, "canoes": 2988, "sees": 4636, "ball": 68, "ticket": 2617, "KitchenAid": 4404, "inspecting": 1728, "headdress": 2213, "baseman": 3614, "instrument": 490, "materials": 3032, "reading": 215, "Here": 1165, "guards": 2394, "participants": 3478, "bored": 3034, "cloud": 2447, "salon": 2862, "reflection": 1897, "seen": 786, "desk": 612, "At": 1381, "right": 351, "teddy": 3296, "decoration": 4229, "cane": 924, "task": 2853, "show": 587, "trousers": 4172, "shoulder": 538, "mailbox": 3001, "balance": 1382, "emerging": 3976, "measuring": 3239, "hangs": 1117, "bathroom": 1499, "overpass": 2938, "rake": 3671, "spray": 1129, "taxis": 4349, "strums": 4575, "black": 22, "artwork": 1585, "ties": 2717, "relax": 1825, "fliers": 4752, "upper": 2536, "list": 4273, "horizontally": 4922, "go": 750, "10": 3223, "adjacent": 4330, "crane": 1424, "weighing": 4443, "lipstick": 2876, "jockey": 1630, "begins": 2002, "flute": 1813, "pipe": 1093, "mother": 563, "sun": 485, "amplifier": 4946, "windsurfer": 4671, "accident": 2781, "athletic": 1248, "won": 4406, "seesaw": 3442, "roadwork": 4753, "basement": 3297, "turtle": 3340, "array": 3500, "bale": 3527, "partly": 3996, "Dog": 988, "walked": 3050, "link": 2123, "elephants": 3570, "Toddler": 2906, "fly": 1459, "stoplight": 4171, "America": 2772, "cricket": 1517, "1": 2014, "decorating": 4179, "stands": 87, "sled": 841, "antique": 2763, "rugs": 3677, "every": 4911, "muzzle": 2548, "throw": 722, "handful": 4709, "space": 1383, "arranged": 3418, "Amish": 3618, "clerk": 4564, "cooking": 435, "handrail": 2059, "dumping": 4690, "snowboards": 3316, "sell": 1448, "harbor": 2378, "popcorn": 3943, "low": 992, "sash": 3558, "eating": 200, "automobile": 3168, "clothes": 307, "climbers": 2668, "reflecting": 3411, "displaying": 1426, "concession": 3727, "sandwiches": 4531, "massive": 3081, "welder": 4153, "my": 3234, "played": 1870, "sound": 2718, "anvil": 3951, "lone": 961, "track": 306, "Mountain": 4165, "kind": 911, "taller": 4551, "opened": 2983, "scientist": 3011, "him": 125, "carrying": 141, "training": 1602, "dolly": 4761, "shop": 369, "Clause": 4445, "decorated": 912, "four-wheeler": 4414, "follows": 1720, "mountaintop": 2719, "team": 249, "backpacker": 4126, "7": 2720, "sheet": 1126, "curtain": 2571, "9": 3922, "swinging": 574, "seating": 3390, "flying": 572, "tutu": 2500, "vests": 549, "herd": 4001, "sidelines": 2181, "yet": 4524, "bicyclist": 944, "sip": 4313, "drinking": 334, "folk": 4230, "handling": 2260, "season": 4875, "heat": 4916, "workshop": 2159, "stairway": 2063, "mustard": 4425, "burgundy": 2191, "barefoot": 878, "inspect": 2995, "three-wheeled": 4870, "dolphin": 3546, "dozen": 3508, "six": 1198, "elevated": 3193, "waving": 740, "inline": 3385, "seaweed": 3836, "pushes": 904, "muzzled": 3142, "tracksuit": 3155, "indian": 2077, "quad": 3012, "hear": 3528, "formed": 4829, "spiked": 4451, "violins": 3220, "slab": 3686, "blouse": 960, "Coca-Cola": 4093, "leader": 3197, "held": 765, "do": 807, "tour": 2138, "Crowd": 1816, "kayaking": 1613, "hotdog": 2072, "sprinting": 4603, "view": 461, "bare": 1764, "located": 2086, "drivers": 3412, "nail": 2075, "crying": 842, "East": 4460, "snack": 1649, "fishermen": 3798, "electronics": 3730, "dome": 4974, "butcher": 2907, "cast": 2327, "short-sleeve": 2750, "exercising": 2742, "away": 344, "potato": 2683, "corner": 406, "playground": 475, "cook": 1437, "rise": 4659, "Japan": 4258, "patiently": 3110, "filming": 2494, "pillars": 2698, "attractive": 2282, "concentrating": 3514, "stood": 4629, "driven": 2602, "lollipop": 4148, "barber": 1405, "pajamas": 1178, "fishes": 2131, "check": 1909, "african": 1431, "already": 4928, "bars": 1258, "own": 1931, "watermelons": 3076, "Some": 444, "Busy": 4562, "devices": 3350, "serve": 2026, "taken": 936, "pavement": 990, "handstand": 1378, "Workers": 1028, "bed": 458, "pots": 2235, "fighting": 695, "practices": 1844, "motocross": 1410, "taking": 163, "pretty": 1579, "fashionable": 4723, "release": 4817, "foliage": 2428, "mask": 579, "pin": 2676, "tug": 4978, "retrieving": 3258, "thought": 3259, "racetrack": 1177, "balancing": 1027, "squirrel": 4691, "flames": 2725, "bar": 397, "polka-dot": 3987, "cries": 2749, "awaiting": 2736, "stacked": 2733, "convertible": 4201, "shady": 3748, "podium": 1169, "observes": 1839, "want": 4901, "sumo": 3450, "jack": 4351, "speech": 1308, "metallic": 3364, "works": 498, "hat": 64, "begin": 2604, "columns": 2268, "litter": 4852, "relay": 3228, "civilian": 4947, "crown": 2167, "finishes": 4350, "props": 4923, "fine": 4831, "toddlers": 1962, "professional": 1074, "javelin": 3336, "poodle": 2369, "Bikers": 3871, "camouflage": 951, "pitbull": 3837, "starts": 3786, "inflated": 2939, "taxi": 1525, "bike": 99, "accordion": 837, "tubes": 3625, "job": 1427, "coconuts": 4341, "everywhere": 3283, "woodworking": 4180, "clinging": 4808, "sized": 1871, "wristband": 4620, "pitcher": 1143, "Cowboy": 3396, "wagon": 1215, "over": 72, "rope": 370, "spins": 2964, "combat": 3770, "sporting": 1403, "thumb": 2798, "roller": 964, "fingers": 1175, "sheep": 1280, "lighthouse": 4683, "monopoly": 4578, "vault": 4684, "Motorcycle": 4364, "factory": 1682, "striped": 184, "plywood": 4939, "metropolitan": 4685, "middle": 258, "creates": 3468, "outstretched": 1485, "waits": 780, "On": 1170, "hoods": 4921, "ukulele": 4894, "case": 1562, "Skateboarder": 2554, "found": 3549, "sides": 1593, "bags": 417, "conference": 1518, "sniffing": 2559, "physical": 4960, "stacking": 4488, "onto": 345, "aisle": 1886, "thrown": 1120, "background": 90, "tools": 1261, "parachutes": 3952, "casual": 1647, "Shop": 4514, "uniforms": 327, "sneakers": 1296, "cutting": 506, "suburban": 2652, "standing": 32, "food": 148, "company": 2106, "snacks": 2279, "unloading": 3130, "hook": 3179, "door": 476, "soldiers": 1434, "sweat": 4078, "campfire": 2422, "cookie": 2943, "powder": 3771, "squirt": 4469, "strumming": 3988, "frames": 3838, "eats": 930, "important": 3890, "both": 366, "'": 890, "camping": 1685, "sleepy": 4895, "shape": 2454, "fog": 2901, "hit": 527, "hands": 159, "fireman": 1800, "graffiti-covered": 4020, "blanket": 606, "bank": 1532, "study": 4270, "hug": 1784, "decorations": 2324, "tights": 2038, "balls": 805, "married": 1582, "clothesline": 2989, "kissed": 4968, "wet": 544, "tying": 2636, "beauty": 4342, "fist": 2777, "sideline": 4809, "leashes": 3013, "prepared": 2549, "Pedestrians": 2024, "shaving": 1092, "cliffs": 4605, "shovels": 1607, "snaps": 3979, "bust": 4763, "mist": 4149, "system": 2708, "gorilla": 4857, "snowboarders": 4128, "woods": 440, "accepting": 3864, "lowered": 4747, "adjusts": 2230, "lean": 2015, "bib": 2293, "banana": 2795, "piano": 1020, "dried": 2969, "competition": 646, "Obama": 3697, "note": 3095, "gay": 4285, "radio": 2974, "bracelet": 2854, "violinist": 3959, "earrings": 2481, "trick": 324, "gowns": 3672, "arena": 1132, "chinese": 1745, "kettle": 4358, "crouched": 1840, "orchestra": 1456, "enthusiastically": 4286, "hippie": 4813, "product": 2328, "Star": 4215, "pause": 4247, "neck": 880, "Great": 3756, "meter": 4053, "its": 216, "blue": 26, "expensive": 4807, "points": 957, "plain": 2313, "cigar": 2831, "knitted": 3953, "signs": 661, "maker": 4397, "dominoes": 3817, "troupe": 4741, "festival": 929, "skyscraper": 4536, "watery": 4633, "cotton": 2206, "battling": 3800, "skull": 2560, "plastic": 420, "lavender": 3652, "girlfriend": 3924, "cowboys": 2370, "waring": 4344, "caucasian": 2354, "rafting": 2605, "leaping": 769, "stick": 304, "High": 4024, "boulders": 4515, "skips": 4838, "pretends": 3446, "rounds": 3447, "receives": 3505, "Group": 605, "touches": 1872, "canned": 4315, "batons": 4835, "dyed": 3284, "against": 229, "muddy": 915, "percussion": 4567, "toss": 3591, "stuffed": 899, "saris": 3903, "pretzels": 4181, "pile": 586, "person": 63, "cargo": 2092, "turtleneck": 3801, "indoor": 954, "old": 169, "work": 236, "princess": 3506, "flip-flops": 1541, "goggles": 552, "clothing": 242, "without": 1090, "suds": 4606, "cooks": 1759, "boot": 3905, "money": 1204, "suite": 3177, "satchel": 4660, "expression": 1980, "neon": 1216, "camera": 104, "blowtorch": 4110, "African-American": 1817, "painting": 326, "bikers": 1398, "planks": 4529, "cookies": 3103, "Marathon": 3387, "Male": 1358, "bent": 1163, "Black": 775, "rubs": 3560, "glider": 4029, "eat": 848, "disk": 3909, "stall": 1847, "tracks": 788, "artist": 744, "hedge": 4924, "equestrian": 3315, "locomotive": 4634, "cameraman": 2067, "pulls": 1067, "teammates": 1942, "protecting": 4407, "no": 529, "tire": 857, "siting": 2842, "self": 4083, "inside": 266, "hammers": 4233, "No": 4908, "sauna": 4097, "Soldiers": 3030, "lawn": 486, "slung": 4129, "sells": 1329, "dolls": 2924, "races": 1679, "suits": 541, "bay": 2592, "boxer": 2040, "mural": 976, "ten": 2737, "flip": 888, "using": 210, "vine": 4816, "sleeveless": 1401, "faced": 4600, "Police": 1722, "shadow": 1441, "hammer": 1156, "sheer": 3304, "vacuum": 2726, "flags": 582, "large": 57, "riding": 80, "horse": 206, "spraying": 1778, "storm": 3529, "various": 644, "mounted": 2833, "constructed": 4289, "plush": 3955, "incline": 2996, "trying": 269, "paints": 1085, "waiter": 2637, "papers": 1064, "sites": 4332, "am": 4775, "sparklers": 3772, "galloping": 4453, "lines": 1446, "designs": 2252, "dark-skinned": 1173, "wand": 3676, "swings": 732, "tournament": 2283, "written": 1757, "Rugby": 4200, "cartoon": 3423, "airborne": 1316, "lion": 2578, "agility": 3673, "rubbing": 3773, "waiting": 245, "framed": 2308, "flowered": 1282, "tow": 3539, "slam": 3062, "worn": 3070, "adults": 364, "landing": 1967, "living": 1040, "adding": 4843, "pub": 3589, "keep": 2339, "extremely": 3550, "scratches": 4214, "Snow": 3826, "strike": 2346, "scarves": 2455, "carves": 4918, "tags": 2448, "beautiful": 447, "synchronized": 3148, "brushes": 2093, "beginning": 2662, "tambourine": 4169, "York": 1190, "hooded": 972, "horses": 504, "groom": 1031, "flour": 3123, "foods": 2356, "senior": 2940, "kicked": 2274, "performers": 1257, "enjoys": 1063, "cellular": 4104, "doctors": 2886, "moped": 1916, "plaza": 1291, "moves": 1116, "gallery": 1900, "completely": 2793, "similarly": 3235, "vehicles": 1492, "motorbikes": 2930, "everyone": 3574, "stars": 2403, "crab": 3891, "backhoe": 3856, "cheerleading": 2834, "waterfront": 2895, "frame": 1283, "kicking": 624, "and": 7, "except": 3960, "web": 4426, "jacket": 79, "black-haired": 2132, "trucks": 2383, "teaching": 1648, "graffitied": 3857, "grinning": 4163, "professionals": 3971, "designed": 3462, "skirt": 388, "peaks": 4236, "overweight": 1936, "had": 1688, "arched": 3840, "transportation": 1512, "surfing": 687, "historical": 4166, "wheels": 1500, "because": 2782, "tugging": 3272, "lips": 2238, "Segway": 4168, "are": 14, "forms": 3171, "saddle": 3388, "sticker": 4989, "yo-yo": 3374, "trainer": 3402, "watercraft": 4310, "headphones": 749, "community": 2551, "float": 1546, "collar": 755, "chainsaw": 1992, "superman": 3823, "pay": 2190, "action": 1471, "bakery": 2791, "all": 230, "jewelry": 1567, "armor": 3928, "racket": 934, "brochure": 4755, "session": 4949, "camper": 4380, "end": 946, "french": 3232, "Eastern": 2555, "gesture": 2083, "tea": 1851, "house": 347, "site": 680, "tattoo": 821, "licks": 2858, "Bank": 4940, "playhouse": 3940, "scooter": 719, "recipe": 4814, "Yellow": 3270, "college": 1435, "examines": 1752, "tablecloth": 2564, "Cyclists": 3169, "bandage": 4581, "tongue": 950, "trays": 3803, "rest": 1123, "jug": 4054, "brushing": 1363, "shallow": 792, "zebra": 4251, "reach": 1583, "jog": 2824, "asian": 428, "toothbrush": 2296, "nothing": 4288, "itself": 3252, "flowing": 2586, "German": 1324, "headscarves": 3551, "skin": 2985, "potted": 3834, "Old": 1144, "items": 641, "bath": 1667, "Kids": 823, "silver": 639, "cowgirl": 4655, "train": 232, "pair": 926, "viewed": 3648, "Tourists": 2139, "handles": 3104, "necklace": 1304, "ramps": 4150, "golfer": 2752, "narrow": 1272, "chip": 3699, "Race": 3337, "barbecue": 1239, "promoting": 4963, "cigarette": 474, "protest": 1511, "clad": 1733, "basket": 628, "balcony": 993, "bubble": 1148, "aircraft": 4480, "cherry": 2565, "breaks": 4734, "man": 9, "helped": 3265, "favorite": 3375, "public": 408, "washing": 859, "Smiling": 2566, "maybe": 3026, "cheeks": 3063, "elegant": 3819, "elevator": 2792, "children": 69, "service": 2417, "sing": 1480, "extends": 3829, "occupied": 4036, "toast": 3314, "batter": 1810, "raft": 1171, "subway": 386, "speaker": 2287, "helmets": 689, "youths": 2613, "scarf": 437, "puddles": 4576, "Shoppers": 3531, "circles": 3981, "collect": 4944, "overlooks": 2468, "activities": 3009, "best": 3331, "mountains": 453, "guy": 186, "junk": 4252, "shading": 4898, "move": 1011, "island": 3787, "collecting": 2908, "seems": 1036, "tub": 1377, "really": 2485, "let": 4586, "eagle": 4194, "singing": 268, "Snowboarder": 3010, "knives": 3906, "Surfer": 3236, "practice": 1212, "crew": 1149, "jogs": 2153, "positions": 4781, "paper": 337, "rollerskaters": 4891, "crayons": 2325, "sliding": 760, "hooping": 3209, "pigtails": 1863, "upwards": 2579, "chisel": 3263, "color": 1337, "ultimate": 3948, "tote": 3851, "fork": 3603, "Hotel": 4925, "lady": 135, "blows": 1375, "skate": 875, "Skier": 4676, "exercises": 3486, "raincoat": 2515, "installing": 4198, "fit": 2926, "ski": 727, "thinking": 3230, "information": 2193, "referees": 4369, "snowboard": 1105, "lays": 863, "guiding": 3298, "sunlight": 1937, "like": 350, "men": 34, "peace": 1297, "racers": 1978, "teeth": 896, "adjusting": 1921, "teens": 2187, "peering": 2390, "windbreaker": 3578, "either": 1130, "assistance": 4563, "assorted": 3907, "rounding": 3703, "bear": 1670, "involved": 2904, "portrait": 2094, "ritual": 3562, "treat": 2632, "through": 62, "paddling": 1245, "level": 2685, "hikers": 1341, "racquet": 2796, "earbuds": 3873, "monument": 2115, "fireplace": 2822, "bowler": 2764, "bearing": 3638, "three": 189, "joke": 4972, "camel": 1913, "mainly": 4375, "kiosk": 2402, "dot": 1880, "Members": 4037, "puppy": 1138, "soldering": 4827, "sparks": 2745, "suspenders": 2016, "strawberry": 3466, "Family": 2463, "Biker": 4321, "facility": 2871, "tips": 2855, "jerseys": 1161, "wine": 1099, "jersey": 470, "horizon": 2397, "daily": 3586, "Rollerblades": 3557, "shoulders": 791, "science": 2298, "gentleman": 521, "sorts": 3611, "climbs": 645, "help": 989, "Wall": 3982, "building": 78, "mascot": 2893, "ax": 3154, "adorable": 3898, "she": 278, "wrapping": 3134, "bronze": 3782, "orders": 3920, "runway": 4582, "cannon": 3448, "chested": 4384, "noses": 3935, "customers": 1330, "bringing": 3702, "simultaneously": 3389, "topped": 3649, "watch": 219, "Golden": 3491, "social": 2776, "monk": 2986, "prize": 4583, "barrels": 3441, "legs": 623, "lasso": 2456, "beverage": 1288, "sings": 688, "camp": 2639, "laboratory": 2239, "cars": 519, "bee": 4316, "Irish": 4462, "feeds": 3056, "pull": 1335, "takeout": 4736, "symbols": 3700, "hard": 339, "axe": 2180, "Child": 1046, "red-haired": 1231, "dinosaur": 2630, "frowning": 3908, "drill": 1777, "juggling": 1109, "leggings": 2269, "cabinet": 3563, "cash": 3043, "shouting": 4084, "hardwood": 2584, "overhead": 1644, "staircase": 1089, "mohawk": 2154, "off": 116, "lift": 1241, "edge": 449, "officer": 756, "touch": 2165, "hawk": 4637, "cupcake": 4585, "Looking": 4398, "walker": 3126, "tagged": 3759, "haircut": 1238, "vegetable": 1596, "crafts": 1768, "shorts": 123, "guitars": 1000, "viewer": 2965, "badminton": 2799, "gondola": 4226, "very": 279, "cab": 2338, "older": 119, "lockers": 4810, "profile": 4187, "laptop": 733, "desolate": 4702, "guarding": 3804, "harnessed": 4355, "flower": 633, "rehearsing": 3983, "assist": 4602, "martial": 539, "placed": 1835, "retail": 3954, "feed": 4109, "British": 2423, "kick": 726, "socializing": 2311, "squad": 3492, "glances": 4663, "print": 1233, "fountains": 2973, "bending": 1106, "tug-of-war": 1865, "dart": 4512, "join": 3931, "daylight": 4447, "farmer": 2178, "fish": 479, "soil": 3158, "tiny": 1926, "fixing": 799, "bites": 2608, "stirs": 3159, "poles": 1049, "tuxedos": 3410, "better": 3687, "billiards": 3991, "scooters": 2076, "after": 374, "sweater": 284, "laid": 2614, "knees": 1428, "aged": 2201, "chocolate": 1945, "weaving": 1786, "angle": 3650, "gazing": 2256, "same": 635, "Firefighters": 2478, "fruit": 535, "scissors": 2449, "crawling": 2843, "involving": 2317, "chickens": 3147, "Korean": 3633, "coconut": 3339, "pet": 2347, "books": 879, "shelves": 2916, "story": 2156, "confetti": 3356, "enclosed": 2891, "act": 1672, "talent": 3729, "statues": 2284, "Patrick": 4485, "She": 3605, "murky": 2856, "hovering": 4465, "shoeshine": 4482, "participating": 1259, "hairnet": 3859, "hearts": 4446, "forward": 1359, "pitches": 4726, "ceremony": 1548, "printed": 2011, "loud": 4738, "onlooker": 3831, "oven": 1947, "far": 1859, "emergency": 2440, "quick": 4876, "clean": 1187, "does": 439, "snowing": 4532, "machete": 4566, "ordering": 2942, "odd": 2171, "backseat": 2669, "disc": 2594, "bench": 146, "captured": 3434, "wrestler": 2095, "wetsuit": 938, "equipment": 432, "writing": 648, "dark-haired": 673, "embraces": 3821, "getting": 250, "cap": 231, "observing": 1230, "Legos": 3348, "stationary": 4268, "dragging": 2374, "overlooking": 638, "letter": 3926, "include": 4951, "coffee": 609, "Woman": 248, "canoe": 887, "fun": 763, "besides": 3428, "test": 2867, "stroller": 679, "ornament": 4764, "celebration": 1944, "store": 223, "games": 1747, "missing": 1834, "stomach": 2065, "boating": 4381, "prevent": 4840, "moment": 1829, "fields": 2519, "belt": 1102, "hundreds": 4825, "John": 3186, "packed": 2207, "quilt": 4352, "steep": 1174, "supermarket": 2355, "helmeted": 2972, "listening": 570, "ponytail": 1293, "only": 1042, "character": 3084, "boulder": 2623, "yellow": 58, "rail": 668, "tackled": 2117, "swing": 318, "sailboat": 2091, "pigeons": 1501, "drops": 4209, "barricades": 4926, "receiving": 2562, "direction": 1039, "card": 1694, "appear": 1008, "past": 254, "cellphones": 2275, "acting": 2690, "personal": 4486, "Bicyclist": 4517, "with": 11, "coveralls": 3198, "Olympic": 2144, "fleece": 3271, "await": 3577, "gentlemen": 1400, "digs": 2410, "graying": 4290, "tiger": 2129, "valley": 2018, "vendor": 593, "dunks": 4019, "Boys": 1588, "jogging": 871, "words": 2000, "trombone": 4356, "surround": 2714, "participate": 1864, "short-sleeved": 2089, "the": 5, "sombrero": 4750, "surf": 1153, "height": 3219, "wheelbarrow": 1941, "proud": 4457, "dentist": 4003, "docked": 3628, "pushed": 2486, "!": 1449, "flight": 1247, "says": 691, "contains": 3461, "deck": 877, "lie": 3275, "leaf": 2212, "attention": 1399, "cyclists": 1309, "puppet": 2902, "blossoms": 4783, "mark": 4592, "occurring": 4903, "route": 4610, "clouds": 1662, "commercial": 2615, "people": 19, "manhole": 4550, "snap": 3788, "overcast": 3533, "admires": 4111, "derby": 1624, "skater": 1536, "lap": 682, "School": 2472, "purchase": 2495, "flashing": 4757, "iPod": 3404, "Hockey": 2387, "shaved": 1677, "tanned": 3774, "asking": 2556, "nuts": 4664, "plane": 1118, "auditorium": 2340, "hotel": 1848, "bowing": 3733, "backward": 3555, "learning": 1977, "instructor": 2479, "to": 15, "stockings": 3276, "roadside": 2860, "seafood": 3180, "players": 222, "above": 325, "revealing": 4176, "sews": 4317, "bucked": 4146, "Nine": 3017, "shovel": 798, "bow": 1598, "merry-go-round": 2371, "balloon": 665, "watches": 224, "musician": 928, "making": 262, "arch": 2840, "soaring": 4952, "toys": 810, "ready": 335, "skiers": 2008, "woman": 13, "competing": 736, "trees": 252, "thumbs": 1668, "enjoy": 830, "starring": 3775, "midst": 2004, "graphic": 3565, "parked": 550, "trashcan": 1751, "stretching": 1534, "bears": 3559, "visor": 2811, "tomato": 3876, "machine": 405, "photos": 1478, "rectangular": 4993, "somebody": 3205, "collie": 3357, "drenched": 4557, "pedestrians": 1158, "so": 1395, "cut": 942, "visit": 4274, "lingerie": 4707, "newborn": 1408, "Local": 4314, "twirling": 2596, "haired": 3822, "fills": 4487, "book": 303, "turning": 1673, "trio": 3449, "rolls": 1987, "s": 3596, "hoping": 4665, "Mother": 2638, "Person": 642, "hugging": 815, "wheeler": 2711, "maintenance": 2567, "cutoff": 4006, "compete": 1406, "SUV": 2195, "messenger": 3561, "Students": 2060, "crops": 2593, "soaking": 4055, "shaped": 1447, "Musicians": 2882, "Crowds": 3927, "medium": 2198, "line": 273, "sketch": 4961, "caught": 1203, "support": 2302, "jump": 299, "hiding": 2188, "watching": 166, "travel": 2689, "shoveling": 1140, "Spiderman": 4291, "floor": 226, "travels": 2889, "trotting": 4609, "infant": 1013, "woodland": 3567, "skateboarder": 481, "supported": 4340, "apart": 2667, "memorial": 3530, "congregating": 4318, "beagle": 4030, "U.S.": 3435, "climb": 858, "amused": 3912, "NY": 4044, "larger": 1775, "along": 139, "herself": 1202, "garage": 1415, "mini": 2671, "side-by-side": 4998, "loaded": 2148, "biting": 1379, "muscle": 4574, "Very": 3480, "pass": 753, "surfs": 1878, ",": 12, "duck": 1785, "motorbike": 1234, "nude": 4294, "Eight": 1969, "contemplating": 3716, "littered": 3936, "backdrop": 1531, "straight": 1674, "windowsill": 4269, "available": 4927, "leaves": 491, "horseback": 1589, "Asian": 136, "insect": 4954, "dangerous": 3865, "tank-top": 3473, "draped": 2487, "passenger": 1915, "searching": 3324, "sails": 4085, "light": 277, "entrance": 1423, "crate": 2522, "backpacks": 1222, "rowboat": 2727, "offering": 3192, "shades": 1953, "deep": 925, "vaulting": 4040, "kicks": 967, "barricade": 2954, "squares": 4265, "religious": 1725, "Jack": 4847, "performs": 473, "spiky": 4877, "focus": 2442, "chews": 3242, "assortment": 3761, "could": 4354, "dark": 177, "banner": 1080, "trash": 1001, "heavily": 2336, "crowds": 3637, "crashes": 4785, "rice": 2050, "filmed": 3094, "welding": 1361, "windsurfing": 4507, "parts": 3136, "banners": 2933, "kayaks": 2691, "speak": 1898, "trains": 2501, "robe": 978, "Young": 205, "tired": 2312, "tree": 165, "ad": 3055, "type": 804, "road": 145, "serving": 1164, "round": 1058, "tied": 1393, "set": 367, "hate": 3516, "defenders": 4489, "Cars": 3710, "family": 390, "chefs": 2208, "sweet": 4686, "chained": 4689, "downward": 3554, "base": 714, "behind": 92, "fans": 1079, "This": 314, "washed": 3998, "loom": 1875, "sisters": 4235, "mountain": 234, "watermelon": 2812, "pyramid": 3047, "merchant": 4107, "an": 27, "function": 4320, "judge": 4134, "panel": 3455, "swimsuits": 2017, "followed": 2145, "faces": 700, "chairs": 403, "sports": 589, "floppy": 3319, "plow": 3623, "first": 1254, "spiral": 4681, "softball": 1268, "wife": 2221, "fireworks": 2309, "lamps": 3986, "curved": 2953, "razor": 2585, "beneath": 1551, "bounce": 2633, ":": 3732, "barely": 4520, "out": 75, "wrestle": 1691, "letting": 4711, "advertisements": 2418, "frosting": 4988, "delivering": 3893, "bound": 4534, "little": 60, "Teenage": 4271, "cones": 1223, "tile": 1540, "mud": 843, "court": 537, "darts": 4626, "Closeup": 2844, "exits": 3651, "One": 256, "opponents": 3016, "exotic": 3366, "attend": 4322, "paperwork": 2524, "barrel": 1564, "suitcase": 1568, "hunched": 2814, "sitting": 29, "seagulls": 2609, "bronco": 2634, "studio": 1452, "Bride": 4216, "being": 178, "battle": 2377, "barbecuing": 3135, "Thomas": 4786, "putting": 441, "groups": 1924, "text": 2686, "loaf": 4263, "wares": 1910, "office": 812, "arcade": 1985, "mount": 4456, "caution": 2863, "skyscrapers": 4234, "leather": 616, "van": 920, "innertube": 2913, "crossing": 477, "strange": 1576, "bigger": 4670, "billboards": 4912, "below": 817, "seat": 851, "bowls": 1911, "bikes": 465, "Orange": 3398, "candles": 1663, "drawings": 3985, "toward": 448, "lively": 4746, "hopscotch": 4136, "reads": 532, "late": 2775, "poised": 3992, "Sports": 4490, "buckets": 1496, "trolley": 2133, "not": 884, "pasta": 4905, "blower": 3285, "sweeps": 1950, "menus": 4930, "underwear": 2033, "colourful": 4919, "rush": 3041, "apartment": 1586, "ocean": 233, "residential": 3391, "singer": 917, "repairs": 2343, "dye": 4390, "metro": 2765, "has": 114, "native": 1537, "Miami": 2813, "flag": 396, "award": 3204, "pacifier": 2692, "kimonos": 3753, "napping": 3059, "dental": 3627, "crowns": 4329, "used": 2411, "sleeping": 340, "dirty": 816, "bride": 684, "rollerskating": 1922, "river": 312, "kneeling": 651, "turkey": 3073, "surfer": 585, "warning": 4287, "somewhere": 2326, "shoppers": 2457, "magazine": 1396, "greens": 4860, "lunges": 4549, "perhaps": 2629, "removing": 3308, "bring": 4593, "lounging": 2124, "arrow": 3027, "solo": 3416, "iced": 4239, "bug": 3910, "jazz": 3599, "coverings": 3734, "frozen": 1981, "teenage": 767, "checkout": 3261, "squinting": 4102, "cone": 1119, "follow": 2331, "plates": 1547, "petals": 4217, "lumber": 3972, "drinks": 545, "bald": 696, "splashed": 2172, "Cyclist": 3762, "doorway": 781, "tropical": 1779, "The": 45, "owner": 2051, "engaged": 1702, "raised": 1026, "poses": 463, "spotted": 2007, "platter": 4692, "wood": 416, "partially": 1718, "plaid": 412, "upon": 1622, "cityscape": 3018, "progress": 2803, "need": 4114, "6": 2090, "sold": 3190, "upward": 2458, "snowshoes": 1932, "spoon": 1740, "11": 4071, "pop": 3384, "nurses": 3035, "pant": 4622, "balconies": 4513, "interviews": 4859, "sprinklers": 2941, "beams": 2815, "jet": 1769, "featuring": 2367, "blood": 2294, "climbing": 247, "sample": 4213, "swimming": 253, "roll": 2048, "scaffold": 2194, "sweep": 3745, "called": 1560, "preparing": 385, "worked": 4444, "position": 1387, "state": 4538, "Adult": 4353, "sailboats": 3548, "sink": 1529, "structures": 3980, "newly": 2885, "driver": 1139, "popsicle": 4907, "smoking": 488, "flips": 1919, "female": 195, "master": 4844, "firefighters": 1796, "calling": 4544, "mustached": 4815, "sandy": 721, "dance": 365, "strikes": 2993, "flies": 968, "attaching": 4086, "People": 81, "objects": 1411, "facial": 2318, "Angeles": 4749, "another": 76, "darker": 4492, "most": 1678, "Five": 353, "bell": 4027, "dummy": 4739, "tattoos": 1218, "fat": 2722, "conversation": 640, "blade": 4640, "paintings": 2542, "screens": 3255, "recording": 2572, "applies": 2807, "casino": 2534, "shake": 3818, "bodies": 4839, "midair": 430, "while": 24, "candle": 2262, "shoot": 1497, "wool": 3222, "carefully": 1822, "following": 1739, "yawning": 3046, "warehouse": 2315, "practicing": 560, "ingredients": 2474, "goat": 2173, "bongo": 4402, "miniature": 2263, "sorting": 2543, "upright": 3301, "point": 1811, "buys": 4057, "day": 192, "cheerleader": 2660, "horn": 1997, "soda": 1645, "real": 4641, "eight": 2597, "circuit": 3200, "skiing": 751, "suspended": 1211, "brass": 2087, "dock": 558, "raises": 1450, "?": 2573, "car": 144, "acrobatics": 4758, "sunset": 698, "interviewed": 4508, "meats": 3957, "engage": 3064, "opposite": 1127, "concrete": 423, "passerby": 4422, "barren": 3105, "stethoscope": 4272, "sipping": 3413, "European": 2687, "toe": 3173, "Two": 16, "mechanic": 4056, "theme": 3816, "chin": 2196, "flannel": 2319, "near": 85, "moon": 3894, "image": 1066, "parallel": 3077, "young": 23, "bucking": 1208, "hip": 2956, "pointing": 554, "bazaar": 4598, "bun": 4760, "guests": 3309, "dead": 1805, "crayon": 4448, "netting": 4977, "bikinis": 2379, "lay": 1609, "Chicago": 4212, "couples": 1831, "alleyway": 1957, "milk": 2215, "overcoat": 3237, "wok": 4591, "rollerblades": 2084, "entertaining": 2158, "It": 1823, "carpenter": 4248, "fisherman": 1608, "crosscountry": 2186, "flea": 3286, "rings": 2197, "formally": 3790, "hats": 275, "rather": 3777, "display": 557, "interesting": 2074, "ATV": 1707, "finished": 2880, "dough": 1948, "stool": 1095, "pets": 2987, "hall": 1557, "catcher": 1354, "sprinkler": 1650, "bandanna": 999, "Tourist": 4874, "Apple": 4135, "trail": 492, "playful": 4693, "Firemen": 3444, "steering": 2881, "English": 3498, "Seven": 1368, "Bull": 3302, "covers": 1770, "flooded": 3352, "letters": 2348, "skateboarders": 3247, "stopped": 1520, "wading": 1563, "cheer": 2066, "attempt": 1507, "citizen": 4155, "kiddie": 3367, "convention": 2804, "motorized": 2119, "contest": 2109, "sons": 4612, "jumps": 185, "headgear": 3229, "leaps": 637, "jeans": 132, "bit": 3911, "ancient": 3160, "telescope": 862, "where": 472, "crashing": 2350, "sculpture": 822, "bucket": 583, "beads": 2103, "sure": 3604, "US": 2655, "security": 1572, "railing": 577, "village": 1571, "probably": 3392, "vest": 308, "student": 1392, "gravel": 1374, "turn": 802, "gesturing": 2278, "footballer": 4501, "fire": 402, "riders": 1141, "package": 2771, "tripod": 1976, "Small": 982, "Frisbee": 497, "happening": 3399, "In": 738, "Dancers": 3248, "we": 2550, "strapped": 2149, "backstroke": 3206, "war": 3317, "pigs": 4408, "oddly": 4427, "son": 761, "T-shirts": 4363, "carried": 3509, "projection": 4842, "opens": 1836, "skinny": 1895, "spots": 2666, "bodysuit": 3303, "bunny": 2868, "ladder": 581, "meal": 656, "ropes": 1521, "nearby": 457, "bends": 1756, "incoming": 3958, "temporary": 4658, "wilderness": 2677, "Number": 2925, "beanie": 1828, "fight": 889, "learn": 4695, "duffel": 4391, "ran": 4042, "foot": 754, "soup": 2921, "easel": 3014, "meat": 746, "pumpkin": 2137, "makes": 588, "shiny": 2174, "thin": 1734, "Britain": 4979, "bounces": 4319, "closely": 1797, "Father": 3326, "bagpipe": 3665, "wheelchair": 1072, "khaki": 921, "restaurants": 4337, "brightly-colored": 4504, "workers": 257, "symbol": 3969, "heading": 2425, "dad": 2222, "shawl": 2225, "backwards": 1227, "wooden": 227, "sponge": 3749, "front": 38, "collared": 1599, "iron": 1889, "cigarettes": 2535, "rider": 468, "rifle": 2280, "whistle": 2508, "packing": 4932, "notebook": 2035, "motorcycles": 1034, "here": 2489, "tan": 272, "sat": 2845, "pouring": 970, "turns": 1879, "given": 3518, "balding": 1418, "dreadlocks": 1584, "mess": 2914, "cubicle": 3552, "wall": 109, "shore": 522, "hips": 2678, "sunshine": 3581, "batting": 4368, "chalk": 1803, "horse-drawn": 4433, "museum": 1315, "Adults": 2789, "run-down": 4530, "off-white": 4673, "embrace": 1928, "clock": 2391, "carve": 4580, "waterway": 2406, "leashed": 3717, "single": 1552, "cleaning": 500, "crouches": 1466, "interested": 3642, "belts": 2734, "small": 73, "soccer": 122, "maneuvers": 4744, "browsing": 2432, "United": 4206, "Elderly": 2001, "planting": 2216, "washer": 3424, "cockpit": 3925, "carriage": 1321, "dumpster": 2392, "cellphone": 291, "minivan": 4130, "stringed": 2209, "Radio": 4955, "employee": 2351, "saying": 1901, "medals": 4466, "crack": 4962, "huddle": 2297, "Man": 107, "barefooted": 2709, "amidst": 1787, "cello": 1804, "head": 157, "landscape": 1045, "Dogs": 2349, "cleaner": 2654, "nature": 1866, "playfully": 2005, "lush": 2583, "foreground": 630, "claps": 4788, "threw": 3074, "knock": 4385, "surface": 1014, "lamp": 1527, "bagpipes": 1964, "build": 2433, "stepping": 2248, "Blond-haired": 4777, "fancy": 1616, "harvesting": 2912, "towels": 3763, "hills": 1982, "lonely": 4789, "dunk": 3065, "floral": 1111, "dancing": 239, "ears": 1137, "shows": 734, "shaded": 3407, "nearly": 2976, "images": 2111, "pig": 2738, "umbrellas": 824, "bicycle": 161, "rolled": 2032, "Ice": 3430, "hiker": 1151, "conversing": 1128, "mixing": 1712, "cycle": 3646, "limbs": 4043, "spectators": 634, "gingerbread": 4727, "examining": 1115, "billboard": 1664, "air": 105, "looking": 50, "identical": 2303, "fluorescent": 3842, "cans": 2118, "nighttime": 1808, "streets": 681, "press": 4688, "sculpting": 2980, "enclosure": 3277, "this": 604, "protect": 3594, "gather": 601, "collection": 2951, "beans": 3843, "stacks": 2884, "campsite": 3162, "denim": 975, "Picture": 3778, "customer": 1680, "pictures": 462, "swampy": 4782, "suit": 191, "upside": 809, "her": 40, "onesie": 4382, "piercings": 4878, "kitten": 3806, "enthusiastic": 4421, "tribe": 4539, "silhouetted": 2927, "within": 1979, "chunk": 4861, "photographers": 2358, "sale": 1103, "scout": 3280, "snowboarding": 1301, "pilot": 2616, "drum": 789, "wrestlers": 2245, "Oriental": 2413, "tilted": 4196, "he": 181, "mill": 3287, "\"": 149, "medieval": 2715, "Claus": 2808, "Bike": 3974, "picking": 973, "victory": 2466, "harp": 2915, "stripe": 1999, "sledding": 2150, "'s": 110, "cover": 1519, "lower": 2700, "demonstrating": 2169, "30": 4958, "entering": 2249, "booth": 873, "Female": 1462, "members": 834, "holes": 3620, "cats": 3269, "leg": 699, "chatting": 1854, "dune": 1569, "checked": 2426, "say": 2850, "beverages": 2250, "cows": 2372, "heads": 892, "nose": 849, "sculptures": 3438, "twin": 4045, "businessmen": 3601, "shirtless": 407, "bicycling": 2728, "during": 240, "extending": 4170, "observe": 1620, "vessel": 4372, "modern": 2037, "league": 3131, "vending": 2264, "Children": 357, "sweeping": 881, "way": 670, "muzzles": 3481, ")": 1220, "fluffy": 1656, "Coca": 4821, "newspapers": 2036, "Market": 3393, "(": 1232, "crib": 3156, "mouth": 187, "beach": 89, "trailer": 1628, "juice": 1905, "determined": 4096, "vintage": 2870, "Caucasian": 1686, "leaning": 373, "wearing": 18, "driving": 496, "gated": 4219, "telescopes": 4228, "garments": 4058, "tackle": 1498, "filled": 501, "13": 3595, "spatula": 3666, "tide": 4386, "appears": 418, "distance": 459, "Soccer": 1594, "boards": 2047, "defend": 4537, "stripes": 1327, "hopping": 3510, "safe": 4579, "climber": 1032, "lots": 1159, "wedding": 602, "demonstration": 2125, "Little": 508, "smoothing": 4141, "hair": 113, "audience": 478, "New": 1065, "paddles": 1729, "weather": 1412, "paint": 597, "embracing": 1966, "tuba": 2826, "march": 1951, "baskets": 1349, "attempting": 649, "backpack": 354, "evening": 1391, "instructions": 4002, "period": 3227, "shirts": 261, "tricks": 866, "casts": 3460, "bowtie": 3678, "pockets": 3377, "hitting": 995, "dunes": 3764, "Someone": 576, "Halloween": 3584, "talk": 631, "scale": 3507, "temple": 2514, "covering": 937, "holding": 42, "goods": 1078, "pieces": 1224, "mossy": 4428, "swims": 1052, "smooth": 3288, "texting": 2785, "seem": 1858, "clarinet": 2978, "covered": 267, "walkway": 717, "up": 49, "sit": 158, "shoes": 348, "on": 6, "Nintendo": 4516, "talks": 565, "slip": 4478, "country": 774, "birthday": 1566, "portraits": 4982, "pierced": 4845, "coming": 709, "half": 1142, "checkers": 2797, "world": 1873, "pictured": 2531, "hill": 287, "motorcycle": 290, "draw": 3096, "debris": 2069, "terrain": 1610, "lit": 701, "donkey": 1642, "gathered": 355, "farm": 1661, "priest": 3606, "winding": 3451, "directions": 1544, "White": 1100, "assembling": 3758, "come": 1792, "beaded": 4072, "nice": 997, "navigates": 3863, "sewing": 1056, "university": 4424, "eagerly": 4245, "tightrope": 3542, "elbow": 3138, "red": 28, "ledge": 715, "hallway": 1246, "escalators": 4762, "calf": 1681, "noodles": 3701, "festive": 2415, "excitement": 2896, "McDonald": 2588, "falls": 1550, "doll": 1701, "forklift": 4561, "poodles": 3844, "each": 168, "Teenagers": 3440, "cleaned": 4644, "wheeled": 2062, "elementary": 3735, "classical": 4324, "over-sized": 4296, "presents": 1920, "picture": 130, "vase": 3755, "gathers": 1590, "sidewalk": 93, "grassy": 294, "keyboard": 1069, "spread": 1530, "examine": 1933, "creating": 1771, "quartet": 4743, "merchandise": 2112, "kid": 387, "Disney": 3791, "walks": 127, "sidewalks": 4818, "project": 927, "blindfolded": 4047, "States": 4677, "tunnel": 965, "fighter": 4139, "portion": 4454, "rooftop": 2098, "shrubs": 4116, "gymnast": 1054, "clutching": 3161, "bales": 4140, "purchases": 4459, "celebrating": 1294, "flowers": 376, "pancakes": 4849, "trade": 4796, "rabbits": 3349, "heavyset": 3415, "discuss": 3470, "chases": 1205, "plant": 1209, "stone": 331, "mop": 1943, "studying": 2203, "ladies": 469, "bows": 3113, "Brunette": 3157, "notes": 1890, "cushion": 3888, "France": 3862, "meeting": 1273, "tomatoes": 2997, "leap": 1761, "peaceful": 3736, "shotgun": 4929, "converse": 1617, "paw": 4493, "outfit": 317, "terminal": 2446, "microphone": 213, "army": 1538, "eyeglasses": 2407, "Couple": 2061, "tap": 4348, "chicken": 1587, "fencers": 4420, "robes": 1172, "spot": 2393, "tall": 424, "placing": 1731, "leafless": 4430, "sunbathing": 3019, "made": 768, "clap": 3420, "green": 48, "alone": 710, "baked": 2970, "sticking": 1219, "present": 1735, "lens": 2679, "orange": 84, "tower": 1711, "snowman": 2753, "as": 51, "architecture": 3456, "wheelchairs": 3525, "wheel": 766, "last": 2766, "shined": 4207, "earth": 3278, "Girl": 611, "handicapped": 4523, "barrier": 1618, "foil": 4855, "mascara": 4063, "rubber": 1473, "pinata": 2104, "shaves": 3058, "drumsticks": 4147, "marches": 4303, "holds": 142, "approaching": 1891, "guys": 342, "instruments": 410, "anticipation": 4765, "cloth": 935, "pot": 1017, "harmonica": 2575, "signal": 3495, "rolling": 1009, "sideways": 2295, "just": 471, "woven": 3020, "pastry": 4202, "seashore": 3783, "donations": 3757, "beater": 4934, "wears": 666, "skeleton": 4526, "slices": 4387, "glasses": 153, "surfboard": 647, "puck": 1263, "Hispanic": 2496, "khakis": 2694, "more": 1660, "any": 4051, "corn": 1558, "floaties": 3358, "houses": 1818, "border": 4771, "skateboards": 1380, "videotaping": 4718, "rifles": 4931, "sushi": 4604, "two": 47, "pond": 853, "microscope": 844, "size": 4697, "Older": 974, "gray": 120, "kilt": 1782, "headset": 3097, "families": 3189, "speeds": 2580, "carnival": 969, "adjust": 4185, "scary": 3895, "huts": 4059, "Wearing": 4519, "hauling": 3463, "tool": 1110, "bull": 615, "raise": 2518, "earring": 4048, "playing": 35, "Santa": 1237, "side": 151, "photograph": 836, "fresh": 1460, "slicing": 3098, "peoples": 3737, "elder": 3005, "tents": 1476, "soldier": 1162, "sign": 203, "peeling": 4865, "snake": 2695, "fuzzy": 3290, "typing": 3170, "depicting": 3488, "stocking": 3403, "All": 3579, "barks": 4890, "pumps": 4887, "railings": 3279, "slot": 3543, "try": 1255, "gets": 655, "blankets": 2041, "stones": 1954, "girls": 98, "glowing": 4249, "theater": 1883, "participates": 3789, "protesters": 2441, "fallen": 903, "cleans": 1671, "watched": 1505, "knit": 1595, "a": 1, "quietly": 4439, "t-shirts": 1342, "gig": 4409, "going": 356, "praying": 2099, "pride": 3746, "cylinder": 4541, "powerpoint": 3877, "accompanied": 2869, "drawing": 907, "hispanic": 3519, "ollie": 4452, "band": 212, "rod": 1972, "rink": 1346, "create": 3439, "shielding": 3766, "casting": 2398, "path": 295, "stadium": 771, "night": 323, "diving": 718, "fighters": 3718, "patrol": 4007, "bad": 4087, "shields": 4188, "slopes": 3640, "Elmo": 2963, "$": 4302, "shade": 1160, "sparkling": 4983, "slender": 4431, "mix": 3496, "chopping": 2271, "runners": 998, "dumps": 4791, "unique": 2746, "ice": 283, "mattress": 3853, "spandex": 3668, "fixes": 2936, "gathering": 694, "free": 1748, "trip": 2162, "assembly": 4292, "feather": 2693, "leotards": 3977, "demonstrates": 3175, "search": 4645, "step": 1331, "communicating": 4812, "nicely": 3150, "bicycles": 658, "Jesus": 3938, "weathered": 4792, "competitive": 2673, "backpackers": 4909, "snowy": 330, "ruins": 2887, "sharing": 1483, "chains": 3289, "performer": 854, "conducting": 2778, "attending": 1626, "approach": 3125, "lunch": 1199, "freshly": 2635, "picnic": 900, "spring": 3051, "Hikers": 4092, "defending": 4497, "roof": 528, "bright": 289, "jackhammer": 4851, "tackling": 2292, "spar": 4411, "mail": 4203, "peach": 3107, "Blond": 1332, "guitar": 129, "canopy": 2710, "attired": 4521, "diver": 2128, "robot": 3211, "uses": 708, "makeshift": 1988, "rimmed": 4186, "pan": 1407, "recently": 3674, "Professional": 4046, "dark-colored": 4733, "soars": 3896, "hotdogs": 2443, "strolls": 3057, "go-cart": 3359, "doors": 1542, "structure": 520, "accents": 4879, "containers": 2199, "motorcyclists": 2568, "wades": 3307, "poverty": 4880, "pit": 1539, "shield": 3939, "Mexican": 2399, "rescue": 2779, "furniture": 1692, "heels": 1210, "electric": 671, "limb": 3515, "focuses": 3932, "likely": 3282, "protester": 3824, "cloths": 3944, "passersby": 2436, "Fans": 4061, "trots": 4735, "laughs": 1249, "sari": 3776, "tray": 1384, "stares": 1122, "bass": 1438, "arms": 300, "backflip": 4984, "places": 2134, "exterior": 4325, "cage": 1794, "attempts": 882, "birds": 1136, "cup": 546, "television": 1789, "referee": 1075, "surfboards": 3807, "bridal": 3226, "next": 70, "turban": 2013, "cafe": 796, "room": 197, "homes": 4565, "Texas": 3291, "marching": 952, "egg": 2382, "barn": 3086, "Sooners": 3191, "Cheerleaders": 2218, "aqua": 2857, "leotard": 2006, "arranging": 4553, "reddish": 2888, "reporter": 4555, "gently": 4846, "touching": 1023, "indoors": 1365, "hoops": 1934, "grounds": 4959, "necklaces": 2723, "chemistry": 4836, "asleep": 838, "youngsters": 4470, "headed": 2052, "waling": 4646, "joy": 2163, "homework": 4367, "hut": 1993, "smiles": 362, "change": 3127, "excited": 1559, "got": 2450, "Baby": 2126, "University": 3115, "is": 8, "Friends": 3028, "restaurant": 260, "Football": 1927, "wait": 692, "bottle": 530, "jumpsuit": 1265, "manual": 4138, "Easter": 3661, "Speedo": 3914, "hooked": 3878, "handheld": 3182, "control": 1643, "cooked": 3482, "gives": 979, "packages": 3260, "smoke": 1114, "parachute": 1888, "shot": 659, "you": 1385, "club": 1150, "TV": 2254, "model": 1317, "pain": 4041, "jar": 3281, "dressing": 3341, "glacier": 4639, "horizontal": 3526, "photographer": 801, "tag": 1404, "hind": 1902, "palm": 1194, "hamburger": 4142, "second": 1528, "extended": 2419, "binder": 4089, "passed": 2502, "summer": 1243, "casually": 1949, "shapes": 3923, "star": 1704, "hidden": 4250, "aim": 4552, "advertisement": 1299, "snowbank": 4062, "lounges": 3825, "samples": 3845, "firefighter": 1955, "sniffs": 3630, "growling": 4299, "weight": 3139, "garment": 2624, "doing": 162, "good": 1285, "abandoned": 3163, "costumes": 543, "crawls": 3116, "poor": 2143, "silly": 1968, "beret": 2219, "news": 3078, "Canadian": 2509, "lei": 4542, "cardboard": 1467, "Groups": 3517, "Guitar": 4481, "Looks": 4237, "grand": 3187, "scoring": 4298, "whole": 2900, "troops": 4554, "sweatshirt": 426, "crafting": 4152, "kept": 4985, "zone": 2465, "Chinese": 864, "dirt": 176, "umbrella": 311, "sister": 2971, "done": 1837, "pedals": 3342, "group": 39, "geese": 3535, "dog": 33, "mechanical": 2780, "opponent": 1275, "leash": 819, "wide": 991, "decide": 4371, "sky": 455, "animals": 1176, "dessert": 3511, "kiss": 1135, "bra": 2527, "white-haired": 2503, "addresses": 3719, "blow": 1697, "overalls": 1029, "storefront": 1522, "forefront": 4491, "trench": 2070, "produce": 865, "lies": 1104, "Christmas": 797, "teacher": 1235, "open-air": 4412, "ridge": 3835, ";": 741, "rocky": 495, "back": 160, "trap": 4614, "flashlight": 4246, "snorkel": 4881, "wear": 949, "bone": 4647, "ripped": 3879, "sight": 3328, "guns": 1515, "push": 1753, "tennis": 218, "uniformed": 1580, "cuts": 1574, "jumping": 94, "rushing": 4615, "drink": 411, "scantily": 4334, "ascending": 4076, "damaged": 3995, "Street": 1444, "marble": 2427, "historic": 4069, "splash": 1716, "shirt": 21, "bystanders": 2420, "scrubs": 2039, "shirted": 3037, "sleds": 3376, "markings": 3207, "Happy": 3880, "couple": 174, "handbag": 2437, "Large": 1443, "desks": 2544, "lime": 2321, "gazebo": 4498, "get": 466, "rollerblader": 3300, "oranges": 2373, "transport": 4133, "youth": 1604, "rocket": 4896, "Rock": 3808, "event": 329, "distant": 3238, "metal": 338, "firetruck": 1306, "finishing": 2510, "market": 274, "belongings": 2304, "beer": 511, "stairwell": 3947, "bag": 243, "skateboarding": 618, "warming": 3368, "dust": 1749, "braided": 2875, "lifting": 1463, "foreign": 1213, "transporting": 3897, "Monopoly": 3556, "purse": 632, "dusk": 1684, "kimono": 3083, "tending": 2569, "rugby": 1062, "kayakers": 3846, "Worker": 3292, "natural": 2511, "jeep": 2310, "surgery": 2140, "catches": 886, "blurred": 2480, "bathed": 4545, "mats": 3087, "fair": 931, "checking": 980, "umpire": 1881, "speed": 1621, "Several": 180, "painted": 489, "oars": 4132, "rollerblading": 1876, "chest": 1094, "pool": 164, "in": 4, "breakdances": 4616, "live": 1726, "illuminated": 2837, "mixes": 3881, "pale": 1894, "girl": 30, "projects": 4577, "Boy": 643, "left": 383, "garden": 739, "breakdancer": 4118, "cat": 782, "patient": 1683, "styled": 3809, "Water": 3921, "Gentleman": 3978, "cooling": 4611, "celebrates": 3244, "coaster": 1867, "bowl": 650, "tourist": 1765, "cobblestone": 1345, "mom": 1482, "shave": 3251, "skates": 1458, "prepare": 1041, "punch": 2525, "dresses": 559, "us": 2552, "jumpsuits": 2557, "fedora": 2821, "wind": 1832, "Concert": 4449, "looks": 102, "weapon": 3874, "pony": 2846, "which": 392, "scuba": 1386, "fall": 1076, "load": 2135, "eggs": 1998, "quarterback": 2644, "athlete": 1289, "focusing": 3185, "farmers": 2451, "leans": 622, "crowded": 380, "name": 1665, "ref": 4336, "matching": 891, "cakes": 4333, "paintbrush": 3453, "make": 580, "rises": 3721, "stainless": 4388, "sits": 96, "Six": 683, "biker": 584, "smile": 517, "addressing": 4191, "length": 3021, "be": 220, "wetsuits": 3351, "n't": 1736, "parking": 592, "crosses": 1310, "walkers": 4502, "stove": 1425, "feet": 566, "pretend": 3693, "gear": 384, "ceremonial": 3513, "braids": 3022, "stunts": 2625, "breakfast": 3052, "rocks": 361, "Musician": 4383, "marsh": 4038, "chaps": 3847, "piled": 3802, "phones": 3099, "wakeboarding": 3427, "struggling": 3240, "Lady": 1068, "surgical": 2621, "passes": 996, "attentively": 4276, "lounge": 2012, "circular": 1874, "offers": 3738, "message": 3497, "violin": 720, "pedestrian": 2121, "graffiti": 443, "home": 567, "mid-jump": 3140, "close": 745, "Girls": 1274, "enter": 2570, "fake": 1783, "working": 115, "laden": 3425, "deserted": 3201, "hose": 1005, "his": 25, "tip": 3810, "penguin": 4751, "tuning": 4607, "asphalt": 2701, "sail": 2589, "maroon": 1262, "dangling": 3667, "boxers": 2461, "earphones": 2504, "undershirt": 4009, "forested": 2729, "selecting": 4204, "scaffolding": 1070, "swimmer": 1305, "puzzle": 3454, "terrier": 3215, "sunhat": 3483, "discussion": 1591, "preparation": 3143, "climbed": 3742, "rose": 3499, "weird": 2957, "lizard": 4417, "block": 778, "see": 923, "nails": 2818, "yarn": 1958, "others": 309, "forming": 3395, "prepares": 561, "zoo": 3664, "trampoline": 833, "During": 2786, "something": 118, "retriever": 2345, "husband": 3414, "blacksmith": 4533, "mops": 4073, "happy": 831, "animal": 653, "mass": 3203, "sledgehammer": 4864, "Lots": 2376, "uniform": 209, "short": 464, "dribbles": 2872, "Kid": 2467, "polish": 2967, "horns": 2928, "paws": 2817, "fairy": 4232, "lights": 757, "towed": 3575, "sponsored": 2859, "child": 52, "slide": 442, "american": 1183, "mane": 4883, "fed": 4283, "India": 2610, "operate": 3033, "landed": 4277, "supporting": 4484, "ironing": 3848, "remove": 4589, "procedure": 4101, "T-shirt": 1397, "concert": 525, "ribbons": 2696, "wakeboard": 3241, "staring": 598, "joggers": 4832, "leopard": 3397, "race": 188, "rock": 170, "cliff": 613, "pathway": 1882, "file": 3072, "himself": 860, "draws": 2618, "town": 758, "monitors": 2740, "sprints": 4240, "formal": 1180, "drying": 3184, "broad": 4373, "laptops": 1799, "Vendors": 4668, "grabs": 2320, "map": 1390, "tunic": 4293, "2012": 2176, "teaches": 3360, "includes": 2897, "rests": 1279, "Africans": 3867, "grilling": 1323, "box": 548, "swords": 2934, "archway": 2948, "number": 421, "hits": 1413, "rapids": 1906, "pans": 3361, "Autumn": 4987, "gaze": 3079, "directly": 2577, "marathon": 787, "football": 207, "performance": 785, "tutus": 3849, "runner": 856, "ride": 280, "lost": 3569, "entertain": 3408, "pushing": 451, "took": 3474, "knife": 1502, "masked": 3882, "Washington": 3919, "parka": 2861, "kinds": 3426, "multicolor": 4275, "Brown": 1469, "bananas": 2475, "portable": 2674, "harnesses": 3233, "sand": 211, "passing": 747, "fellow": 2460, "pauses": 2476, "classic": 2827, "pump": 4543, "mug": 2388, "reaches": 1086, "Hello": 4435, "states": 4525, "autumn": 2234, "salad": 3583, "mustache": 1166, "whose": 2344, "styrofoam": 4910, "patches": 4722, "approaches": 2078, "tight": 1723, "pail": 3805, "carry": 1461, "splits": 3708, "strolling": 3117, "karate": 783, "region": 4472, "chops": 4082, "dry": 1038, "Arabic": 3780, "rows": 1744, "four": 368, "serves": 2598, "cable": 3144, "directs": 3690, "kickboxing": 3023, "meadow": 2342, "register": 3254, "lid": 4220, "Latin": 4434, "Food": 3369, "play": 138, "secured": 4300, "bleachers": 1705, "couches": 4556, "cards": 1432, "served": 2898, "find": 2680, "can": 667, "perched": 2042, "stretch": 2739, "parachuting": 3799, "businessman": 2265, "overturned": 3913, "yoga": 1773, "handkerchief": 4331, "swim": 619, "hood": 1284, "tv": 2576, "organ": 3015, "Onlookers": 3615, "squatting": 1318, "roadway": 2923, "dustpan": 4748, "art": 523, "younger": 610, "platform": 697, "sling": 3868, "fenced": 1419, "bend": 2217, "water": 43, "strewn": 3694, "tickets": 3631, "apparel": 3765, "stack": 1634, "stuff": 2751, "run": 341, "arts": 573, "handmade": 4389, "posters": 2189, "male": 179, "campus": 3218, "positioned": 3616, "chat": 2113, "newlywed": 3607, "marketplace": 1221, "drummer": 1182, "Mom": 4997, "pirates": 4365, "expressions": 4074, "shakes": 2009, "baton": 2979, "one": 46, "advertising": 1710, "booths": 2444, "diamond": 4500, "squirting": 4284, "closing": 3655, "pumpkins": 3915, "truck": 293, "technology": 4745, "performed": 4463, "smock": 3641, "bathrobe": 4715, "too": 2290, "third": 840, "Pizza": 3720, "feathered": 3544, "new": 1006, "professionally": 4632, "candy": 1225, "numerous": 2828, "unison": 3332, "Customers": 2952, "personnel": 2581, "knee": 1145, "needs": 4662, "sleep": 2332, "gate": 1146, "old-fashioned": 3268, "numbers": 1709, "having": 251, "admiring": 2027, "shower": 2023, "long-sleeve": 1416, "silk": 4010, "City": 1603, "strings": 3188, "gardening": 2905, "mixer": 2819, "rooster": 3899, "meditating": 3892, "competitor": 3704, "Mohawk": 1986, "motion": 2110, "blurry": 2255, "shrine": 4699, "hoses": 4694, "organizing": 4714, "fatigues": 2866, "apparatus": 3827, "double": 2505, "driveway": 2227, "capri": 4189, "kayak": 1002, "rally": 1903, "bamboo": 2055, "finish": 1755, "sharp": 2553, "face": 152, "janitor": 3973, "dragon": 2759, "rides": 228, "net": 516, "stay": 3085, "reaching": 845, "shadows": 1938, "dim": 4338, "flock": 2595, "punches": 4205, "gas": 1388, "dusty": 2019, "changing": 3970, "BMX": 1350, "named": 2774, "Navy": 4772, "grinds": 2408, "wallet": 4190, "selling": 422, "write": 3682, "pairs": 3610, "curve": 2141, "necktie": 4990, "vendors": 1929, "playpen": 3617, "bouncy": 3310, "well": 906, "Europe": 3812, "rocker": 4475, "teammate": 1633, "comes": 1917, "romantic": 4716, "curious": 3767, "department": 2314, "waterskier": 4623, "dressed": 74, "mittens": 4509, "buildings": 467, "swan": 3164, "vacation": 4004, "grass": 97, "photo": 379, "carving": 1487, "brooms": 3858, "establishment": 2607, "awkwardly": 4981, "controls": 3406, "teal": 1344, "passengers": 1625, "intersection": 1226, "poking": 3739, "bearded": 676, "punching": 2157, "tossing": 1887, "wants": 4769, "Four": 154, "age": 2401, "coach": 1523, "win": 2168, "attentive": 4850, "moving": 839, "drunk": 4429, "nets": 2204, "sort": 629, "cloudy": 1154, "kit": 4199, "piece": 316, "monster": 4026, "ups": 4011, "five": 731, "chips": 2653, "drumming": 4936, "vibrant": 3335, "stores": 2469, "spike": 2899, "stance": 2820, "pavilion": 4049, "Cafe": 3381, "hula": 1061, "Seattle": 3929, "confused": 3828, "fort": 4570, "Scottish": 3038, "trimming": 3213, "loading": 1640, "wizard": 4621, "goal": 779, "officers": 909, "brown-haired": 1228, "mouths": 1965, "bus": 315, "aprons": 2073, "stop": 621, "types": 2341, "once": 4335, "teenagers": 1073, "entertainment": 4115, "score": 1973, "suitcases": 3916, "coral": 4701, "order": 1513, "vast": 3820, "cords": 4413, "butterfly": 2030, "multiple": 1433, "figure": 1360, "forest": 431, "repair": 1907, "may": 2998, "cultural": 3405, "backyard": 959, "somersault": 4724, "brick": 276, "scruffy": 3962, "stair": 2999, "railway": 3293, "exploring": 3195, "policemen": 2179, "sticks": 813, "celebrate": 2516, "vehicle": 487, "Ten": 4253, "conductor": 2363, "arm": 349, "crash": 3698, "cave": 2787, "folder": 3961, "pigeon": 3320, "shed": 3208, "baby": 155, "chopsticks": 2497, "stunt": 971, "pen": 1635, "beaker": 4164, "spreading": 4667, "weights": 3494, "gun": 876, "breast": 4238, "wild": 2130, "ahead": 1351, "signing": 2434, "husky": 4173, "political": 3202, "culture": 4013, "wheat": 3338, "weapons": 4571, "ribbon": 1556, "belly": 1912, "heart": 1575, "shingles": 4267, "champagne": 2452, "chewing": 1893, "buses": 3262, "chalkboard": 1940, "ping-pong": 3088, "Bearded": 3504, "applying": 1629, "industrial": 2031, "random": 3522, "tackles": 3608, "shack": 3452, "women": 53, "range": 1510, "seven": 1853, "Middle": 2950, "ethnic": 1689, "crowd": 88, "staff": 2523, "downtown": 1311, "Tennis": 4254, "cart": 298, "puddle": 1060, "lock": 4068, "brownish": 4039, "mostly": 1372, "5": 1133, "elderly": 255, "scaling": 2384, "bush": 2333, "sandals": 762, "sheets": 2537, "tank": 322, "snowcapped": 3484, "washes": 2305, "monks": 3108, "diligently": 4648, "colored": 320, "popping": 3811, "dotted": 3679, "polka": 1430, "discussing": 1666, "smaller": 1370, "decorative": 2020, "fixture": 4826, "skies": 2445, "grab": 2270, "Park": 3501, "submerged": 3545, "chef": 943, "give": 2096, "gain": 4587, "slightly": 1657, "Military": 3124, "Shepherd": 2488, "possession": 3174, "hikes": 3379, "hike": 2046, "hairstyle": 4869, "colors": 1003, "tries": 672, "language": 3875, "crouching": 1653, "shooting": 1021, "pillow": 1477, "greeting": 4028, "magnifying": 3779, "meet": 2146, "section": 1793, "aims": 4060, "roping": 3485, "professor": 3688, "logs": 2353, "active": 4650, "unusual": 2300, "hunting": 4871, "delivery": 3576, "pedal": 3636, "Naked": 4471, "seeing": 4339, "shares": 4768, "striking": 2672, "nightclub": 2836, "porch": 1195, "carved": 3477, "Men": 313, "displays": 1899, "device": 905, "rubble": 3490, "aquarium": 2530, "golf": 794, "upset": 2990, "process": 2364, "computer": 438, "pine": 2068, "struggle": 4021, "of": 10, "eye": 1312, "cartwheel": 4012, "banjo": 2231, "racing": 400, "dollar": 4867, "kites": 3568, "gymnasium": 1703, "hilly": 3613, "pedaling": 4374, "hillside": 1612, "drain": 4784, "operating": 1340, "San": 4856, "middle-age": 4473, "neighborhood": 1420, "squeezing": 4305, "pottery": 1654, "lined": 654, "boogie": 2961, "elaborate": 2241, "State": 3945, "construction": 221, "bulls": 4503, "holiday": 2829, "athletes": 1791, "spinning": 1371, "guard": 1167, "shoe": 1147, "me": 3311, "foggy": 3060, "wielding": 3680, "checkered": 1071, "coke": 4866, "raking": 2611, "individual": 1260, "Blue": 2429, "soap": 2334, "wade": 4119, "pulled": 897, "exercise": 1611, "doorstep": 4822, "blocked": 3040, "boa": 4712, "Jewish": 3343, "launch": 3707, "vertical": 3114, "nap": 1367, "highchair": 2272, "partner": 3199, "protective": 1025, "such": 3106, "cob": 4008, "clipboard": 4122, "harness": 1084, "rocking": 2761, "Protesters": 2703, "classroom": 713, "surgeon": 4192, "slacks": 1730, "selection": 3917, "blocks": 1192, "setting": 409, "wakeboarder": 3942, "sausage": 4436, "stuck": 2288, "movie": 1963, "plays": 134, "headscarf": 1516, "upside-down": 2832, "angry": 3071, "bundle": 2991, "song": 1472, "kayaker": 3061, "video": 806, "carpeted": 3536, "machinery": 1193, "raising": 1252, "government": 4938, "awaits": 3619, "These": 922, "descent": 1974, "breathing": 3750, "pink": 91, "Nike": 2960, "concentrates": 4227, "proudly": 3990, "mitt": 3422, "utility": 3054, "dive": 1824, "logo": 1960, "strip": 2085, "mixed": 3004, "Scouts": 4793, "tee": 1846, "brunette": 776, "magazines": 2400, "even": 2874, "studies": 3869, "rural": 1565, "purses": 2526, "airport": 1319, "baking": 3373, "leaving": 1524, "resting": 712, "cop": 2847, "reclines": 3956, "shoots": 2626, "cabin": 3681, "ferry": 3740, "cashier": 3378, "completes": 4437, "start": 1468, "cheering": 1353, "Native": 2538, "grain": 4120, "maneuver": 3145, "redhead": 2920, "peak": 2890, "picker": 3149, "friends": 524, "skills": 2291, "oil": 3112, "adult": 427, "renaissance": 4624, "slowly": 4158, "We": 3165, "patch": 1772, "constructing": 3597, "reviewing": 4255, "mime": 3321, "themed": 3370, "parasol": 4824, "possibly": 1355, "lake": 286, "turquoise": 2100, "circus": 4505, "ATM": 2582, "falling": 894, "dinner": 872, "screen": 693, "grinding": 1675, "3": 608, "silhouette": 1843, "phone": 358, "amongst": 1455, "player": 111, "military": 703, "return": 4221, "tuxedo": 2306, "that": 101, "dandelion": 3994, "railroad": 984, "growing": 4241, "balanced": 3394, "coast": 3151, "ramp": 433, "time": 617, "villagers": 4872, "skateboard": 271, "advertises": 4625, "scene": 578, "care": 2490, "bubbles": 724, "down": 37, "ceiling": 1535, "wheelie": 1841, "brand": 4964, "awning": 2563, "screams": 4672, "tiled": 1930, "interior": 4174, "bikini": 674, "shaking": 1168, "laughing": 404, "brush": 1436, "hurdle": 1184, "japanese": 4820, "sunny": 391, "amount": 2261, "buy": 1706, "prayer": 3152, "pastel": 4399, "square": 939, "buggy": 2949, "wigs": 3900, "zip": 3883, "swimsuit": 1087, "frisbee": 1357, "makeup": 828, "Numerous": 2910, "cruise": 2909, "locked": 4157, "alcoholic": 3598, "seemingly": 3792, "conditions": 4506, "dimly": 1724, "caricature": 3564, "cord": 4326, "facing": 556, "reception": 2385, "parasailing": 3090, "surrounded": 288, "dress": 117, "magic": 4266, "connected": 3121, "tends": 3194, "object": 446, "cause": 3572, "ensemble": 3751, "hang": 1475, "bridesmaids": 2873, "coat": 193, "friend": 898, "blue-green": 4965, "know": 4713, "life": 657, "funny": 1121, "huge": 728, "Olympics": 2021, "stairs": 414, "giant": 855, "exchange": 3752, "females": 966, "brightly": 826, "big": 282, "strips": 4103, "consisting": 2242, "wings": 1506, "wires": 2028, "tiara": 4737, "game": 143, "mothers": 4223, "angel": 2114, "spiderman": 4307, "alcohol": 2688, "purple": 196, "short-haired": 2266, "cold": 963, "drums": 540, "arrive": 4306, "Coke": 4720, "boarding": 2182, "separate": 2757, "greyhound": 1690, "typewriter": 4797, "surrounding": 1179, "kitchen": 296, "convenience": 4123, "banquet": 4225, "darkened": 3433, "choir": 1454, "Day": 3353, "receive": 4124, "shoreline": 1826, "sleeves": 2220, "patrons": 4208, "chain": 1196, "microphones": 1457, "roasting": 4619, "rack": 1994, "brothers": 4222, "was": 1267, "sailing": 2307, "fashioned": 2767, "fists": 4410, "clearing": 2214, "school": 547, "underneath": 885, "throws": 827, "highway": 2122, "mower": 2147, "walk": 150, "statue": 494, "dances": 933, "desert": 835, "oxen": 4956, "mid": 1884, "hand": 131, "backlit": 4415, "place": 664, "avoid": 2962, "motorcyclist": 1394, "scattered": 3224, "rearing": 4906, "snowstorm": 3432, "dishwasher": 3257, "digital": 2471, "Walmart": 2919, "fetching": 3109, "talking": 121, "wig": 1946, "visible": 1250, "pickup": 2981, "open": 301, "activity": 2404, "handle": 2368, "London": 1925, "hiking": 737, "workout": 2650, "lifted": 2170, "tanks": 4794, "liquid": 1474, "Eleven": 4121, "floors": 2917, "racer": 1376, "remote": 3571, "technique": 4651, "pads": 1995, "clings": 4780, "sweatpants": 3153, "competitors": 3593, "dishes": 1514, "pillows": 2656, "bounds": 3937, "Bald": 3118, "whiteboard": 3362, "pitchers": 4893, "Mickey": 4416, "attraction": 3793, "bathtub": 2120, "major": 3429, "trumpet": 1264, "they": 265, "males": 735, "Ford": 4033, "carpet": 1421, "firemen": 1820, "rag": 3102, "would": 4913, "Mouse": 3624, "great": 1714, "multicolored": 825, "catch": 375, "picks": 2277, "whom": 1821, "graduation": 2259, "fires": 4522, "'re": 4754, "by": 44, "entertains": 2647, "sofa": 1417, "monkey": 2043, "jungle": 1639, "matches": 4343, "sizes": 4787, "dilapidated": 3294, "attendant": 3329, "design": 1952, "newsstand": 4125, "glove": 1801, "traditional": 773, "might": 4357, "carries": 518, "crates": 2010, "relaxed": 4652, "War": 4295, "flipping": 1695, "cheese": 2359, "grocery": 846, "hospital": 1256, "laundry": 1030, "torch": 2054, "cathedral": 3538, "greenhouse": 4195, "blocking": 2409, "rainbow": 1440, "owners": 4077, "Band": 2243, "misty": 4967, "Performers": 4231, "opposing": 759, "walking": 41, "products": 1983, "stare": 1857, "engaging": 3647, "helping": 743, "yelling": 2389, "will": 2281, "petting": 1623, "partying": 4242, "tasks": 4438, "strides": 4725, "lead": 1503, "blond-haired": 962, "bands": 4882, "operation": 3706, "adorned": 3068, "snowboarder": 575, "Runners": 2366, "olympics": 4184, "calm": 1737, "Joe": 4841, "unknown": 2704, "controlled": 4957, "soaked": 3965, "awe": 4558, "rafts": 3644, "folding": 1414, "tri-colored": 4680, "destination": 3421, "Subway": 3950, "waterskiing": 2603, "cooler": 3137, "amazement": 4991, "2008": 4594, "Ladies": 3656, "Green": 2721, "diverse": 4297, "vocalist": 4090, "least": 2768, "waves": 594, "picked": 4547, "station": 507, "torn": 3024, "assembled": 3781, "leafy": 3172, "returning": 4618, "contraption": 2116, "defense": 4494, "de": 4256, "busy": 244, "bases": 4156, "dunking": 3830, "led": 3243, "beat": 3141, "button-down": 3256, "grown": 4022, "pajama": 4499, "veil": 3417, "pretending": 2136, "bricks": 1760, "wineglass": 3901, "years": 2992, "aerial": 2246, "plank": 2879, "hanging": 333, "latex": 4483, "breaking": 2848, "Dirt": 3887, "China": 2439, "treats": 4666, "urban": 748, "schoolgirl": 4900, "dancer": 1083, "church": 790, "kneels": 1295, "handed": 3089, "bundles": 4806, "oriental": 1043, "amid": 2421, "national": 4540, "row": 868, "drawn": 1970, "lighted": 2561, "lovely": 4799, "fashion": 2754, "instructing": 4518, "wanting": 4279, "carousel": 2918, "Dark-haired": 4573, "I": 1493, "rainy": 1708, "shown": 1201, "splashes": 1445, "dribbling": 3306, "taught": 4914, "many": 319, "hurdles": 2645, "College": 4756, "hockey": 394, "tosses": 2755, "than": 2470, "African": 450, "abstract": 4992, "Cola": 4805, "jackets": 534, "winds": 3997, "warm": 1328, "banks": 4309, "n": 4131, "oar": 4052, "megaphone": 3007, "across": 198, "cattle": 2810, "McDonalds": 4014, "finger": 1082, "gray-haired": 1655, "limo": 4257, "aiming": 2730, "puts": 1047, "almost": 1991, "cleats": 4917, "cycling": 2152, "Team": 4031, "read": 1509, "skaters": 2731, "breath": 3696, "expanse": 4588, "focused": 2483, "tossed": 4100, "forehead": 1860, "steer": 3691, "mirror": 772, "cross-legged": 3386, "tarp": 2380, "daughter": 953, "member": 1253, "protection": 2663, "scenery": 1849, "raw": 4159, "outfits": 652, "splashing": 916, "projected": 4175, "nine": 4278, "snow-covered": 1555, "mouse": 3039, "center": 932, "curb": 981, "solitary": 4264, "waitress": 2747, "prop": 4854, "toes": 3231, "cute": 2029, "pour": 4345, "peeking": 2648, "masks": 1812, "polo": 1022, "welds": 3964, "basketballs": 4948, "bangs": 4479, "stained": 3657, "lifts": 1918, "cracked": 4976, "Many": 377, "bicyclists": 1302, "workman": 4224, "batman": 3722, "vacuuming": 2877, "escape": 3850, "lip": 3249, "serious": 2945, "mingling": 4649, "bread": 1206, "snowmobile": 3797, "-": 1504, "thread": 4280, "tree-lined": 2744, "Road": 4773, "reflected": 4969, "ages": 1842, "Dark": 4830, "tee-shirt": 3253, "completing": 2661, "dogs": 108, "hammock": 2838, "keeps": 3654, "bmx": 2541, "helmet": 214, "sunglasses": 199, "snowsuit": 2289, "mesh": 3989, "filling": 1767, "ridding": 4527, "still": 1637, "binoculars": 1923, "hydrant": 2424, "gum": 3723, "12": 3512, "chubby": 3532, "characters": 2430, "camels": 2049, "bottoms": 2257, "vegetation": 2758, "You": 3487, "tattooed": 1646, "rakes": 4193, "purchasing": 3345, "tail": 2258, "fencing": 1700, "saxophone": 1112, "daytime": 2329, "sweaters": 2512, "seeds": 3305, "fishing": 395, "circle": 820, "liquor": 3457, "artists": 2184, "&": 1627, "hugs": 1855, "technician": 3537, "hammering": 3069, "marked": 2357, "mannequins": 4766, "cheerleaders": 1244, "Good": 4642, "table": 95, "together": 140, "steps": 372, "defender": 3502, "floats": 2395, "apparently": 3380, "donkeys": 3592, "love": 2707, "land": 1592, "putt": 4458, "year": 4467, "sacks": 3008, "unseen": 3274, "writes": 2064, "students": 660, "divers": 3044, "attached": 814, "wraps": 4975, "problem": 4687, "judges": 3768, "Japanese": 1362, "fix": 1606, "aluminum": 4970, "peers": 1852, "jean": 945, "gift": 2044, "tricycles": 3714, "our": 3653, "workmen": 4259, "injured": 2545, "long-haired": 1287, "scope": 3794, "strong": 4323, "piles": 2646, "features": 3493, "airplane": 987, "greyhounds": 2702, "juggler": 3839, "cow": 1033, "fan": 1713, "wineglasses": 3692, "cowboy": 401, "cheek": 1732, "foundation": 4868, "fur": 1451, "field": 86, "contact": 4050, "sandwich": 1746, "harvest": 4884, "transit": 2513, "baggy": 3119, "roses": 2498, "canoeing": 3975, "share": 1738, "resort": 3709, "organized": 3795, "Boston": 3675, "laps": 4474, "angels": 4654, "lovers": 4675, "converses": 4568, "gifts": 3212, "patio": 1320, "backs": 1298, "lying": 502, "district": 3355, "skillet": 4137, "it": 124, "safety": 509, "xylophone": 3225, "built": 2101, "electrical": 2405, "someones": 3621, "your": 3216, "stoop": 2251, "beside": 285, "8": 2236, "gloves": 515, "cape": 2142, "morning": 2532, "brown": 61, "streetlights": 4943, "mall": 1313, "bottom": 986, "Three": 59, "soft": 2892, "musical": 669, "outside": 56, "haul": 4729, "waist": 1619, "trophy": 2864, "closeup": 1369, "providing": 4704, "slope": 1044, "outdoor": 259, "pizza": 1614, "keys": 4015, "mature": 4597, "sprayed": 2539, "intense": 2606, "spotlight": 2396, "pitch": 1402, "top": 103, "assisting": 3585, "beard": 445, "foam": 2788, "herding": 4800, "ninja": 4999, "beige": 832, "lot": 381, "film": 3322, "themselves": 1124, "scratching": 3273, "sparring": 2712, "target": 2337, "tube": 1185, "pipes": 2622, "Bicyclists": 3832, "piggyback": 2968, "legged": 3540, "shining": 2200, "dump": 3475, "surgeons": 4379, "rig": 4950, "uphill": 2849, "sleigh": 4113, "thick": 2546, "poker": 4301, "laugh": 1277, "drilling": 2600, "tulips": 3325, "handing": 1494, "hamburgers": 3547, "salmon": 4099, "View": 4347, "bedroom": 2412, "rear": 2229, "aid": 4095, "drive": 1717, "dollhouse": 4392, "trunk": 1741, "films": 3267, "worker": 332, "mule": 3318, "canyon": 2977, "barriers": 4064, "should": 3870, "musicians": 770, "knitting": 2056, "power": 1742, "acoustic": 1191, "giving": 505, "empty": 625, "topless": 2335, "patriotic": 4016, "buttons": 3479, "naked": 1488, "word": 1896, "pencil": 2716, "muscular": 2865, "tape": 1780, "laundromat": 2285, "hour": 4731, "wave": 360, "Players": 3520, "cables": 3814, "Outdoor": 4161, "running": 77, "library": 1486, "grandmother": 4210, "kite": 1693, "canal": 2453, "brother": 2286, "scales": 2816, "bracelets": 4127, "crossed": 1442, "digging": 808, "Oklahoma": 3860, "concerned": 4823, "shrubbery": 4260, "things": 1266, "broom": 1338, "Buddhist": 4261, "leaned": 4262, "quite": 4674, "skipping": 3760, "actors": 4418, "else": 2484, "sausages": 3312, "curled": 4419, "furry": 1631, "bridge": 363, "armed": 3724, "motor": 1845, "Rodeo": 4935, "long-sleeved": 1113, "rails": 2878, "fill": 2851, "canvas": 1961, "builds": 4899, "buried": 2506, "sack": 2210, "father": 784, "stand": 106, "cross": 551, "capture": 4106, "chew": 3784, "clown": 811, "gates": 4359, "pole": 359, "wrap": 2520, "under": 201, "lantern": 3683, "branches": 1743, "UNK": 0, "raining": 3711, "Photo": 4401, "bookbag": 4098, "tend": 3933, "stopping": 2947, "rainstorm": 4986, "question": 4638, "checks": 1578, "Starbucks": 4105, "party": 493, "While": 1975, "fence": 270, "luggage": 1048, "releasing": 4858, "underground": 2223, "official": 2800, "dancers": 901, "castle": 1543, "scenic": 1819, "goats": 3458, "string": 1188, "trimmed": 4218, "basketball": 241, "scouts": 2681, "footbridge": 4308, "mat": 1007, "obstacles": 4032, "traffic": 716, "caps": 1333, "attire": 626, "pose": 378, "entertainer": 4728, "cobbled": 3684, "crazy": 3183, "wooded": 725, "much": 2675, "exiting": 2705, "slice": 4801, "tops": 1281, "mowing": 3000, "tightly": 3918, "teams": 568, "high": 292, "groceries": 1827, "split": 3295, "marina": 3629, "variety": 1814, "interacting": 2034, "charcoal": 4770, "branch": 1334, "pulling": 480, "World": 4400, "rowing": 1439, "gym": 705, "USA": 2830, "cereal": 4440, "biking": 1155, "machines": 1984, "extreme": 3120, "adolescent": 3469, "supplies": 1935, "Guy": 1096, "window": 235, "olive": 2735, "riverbank": 2805, "christmas": 2517, "records": 3866, "apple": 1790, "baggage": 4802, "costumed": 2521, "shelf": 2464, "board": 371, "stream": 829, "escalator": 1197, "local": 1053, "French": 3465, "cluttered": 2769, "complex": 3075, "ballerina": 2003, "descends": 4177, "butter": 4108, "flame": 3266, "carts": 1696, "tattered": 4774, "companion": 2966, "bunch": 562, "cupcakes": 4455, "menu": 2299, "drag": 2362, "windy": 4698, "creek": 1481, "pours": 1856, "environment": 1956, "sucking": 3344, "congregate": 3582, "there": 434, "speaks": 956, "cream": 514, "bonfire": 4360, "use": 1207, "goers": 3889, "jockeys": 2748, "traveling": 1600, "Army": 2228, "tin": 4613, "Deere": 4432, "overlook": 3523, "warmly": 2770, "Do": 4915, "bushes": 1465, "bathing": 564, "slides": 1012, "unhappy": 2631, "fountain": 398, "necks": 4902, "newspaper": 542, "twisting": 4885, "glides": 4468, "off-camera": 2045, "paddle": 1356, "complete": 2276, "isle": 4151, "collide": 3769, "looked": 2794, "few": 510, "substance": 2839, "performing": 183, "Hawaiian": 2381, "stump": 2022, "gymnastic": 3796, "speaking": 603, "reclining": 3600, "gymnastics": 1754, "artificial": 3622, "curly-haired": 2599, "displayed": 2164, "populated": 4798, "handlebars": 3080, "curly": 1134, "amusement": 1229, "catching": 850, "keeping": 3705, "halfway": 4661, "Swimmers": 3731, "Wii": 4182, "lands": 2852, "Spanish": 3101, "relaxes": 2416, "pier": 818, "engine": 1762, "screaming": 2649, "throwing": 460, "paintball": 4700, "friendly": 4559, "rabbit": 4070, "chess": 1850, "travelers": 4281, "dorm": 4819, "lobster": 4971, "They": 2492, "times": 4995, "mountainous": 2226, "container": 1189, "starting": 1766, "baker": 4091, "He": 2322, "storefronts": 4730, "smokes": 1366, "bundled": 2438, "loose": 3815, "breakdancing": 2175, "blond-hair": 531, "briefcase": 2160, "cages": 4628, "velvet": 4886, "into": 71, "lanes": 4065, "beers": 2414, "Basketball": 2640, "babies": 2365, "eyes": 483, "flowering": 4679, "surprised": 2493, "tram": 4476, "intricate": 3941, "gambling": 4596, "operates": 2330, "break": 742, "chiseling": 3861, "sweaty": 4378, "picket": 3111, "when": 2627, "ornate": 1758, "descending": 3091, "early": 2883, "but": 958, "captain": 4144, "stirring": 2528, "guitarists": 3632, "bird": 595, "parade": 499, "dives": 2025, "some": 83, "Shirtless": 2473, "bat": 852, "SpongeBob": 3419, "#": 2386, "opening": 985, "shepherd": 2244, "fetch": 2670, "grill": 614, "jars": 4848, "seal": 4495, "these": 2713, "reflective": 1326, "aboard": 3221, "saw": 1464, "marker": 2590, "guides": 4112, "naps": 4377, "series": 2435, "situation": 4669, "seats": 1652, "semi": 3553, "plants": 902, "visitors": 4945, "lets": 4548, "ankle": 4853, "baseball": 175, "shops": 1601, "shaggy": 2183, "listen": 1892, "blown": 4873, "surfers": 2806, "Kitty": 4803, "2": 452, "mic": 2664, "boardwalk": 1364, "retrieves": 4145, "fell": 2946, "lighting": 1861, "their": 66, "bungee": 2955, "views": 3609, "streamers": 3833, "couch": 419, "boys": 137, "prints": 4653, "nun": 2352, "possible": 4088, "inspects": 2507, "homemade": 2151, "dish": 1687, "protesting": 1721, "colorfully": 2273, "deer": 2682, "flaming": 2801, "struggles": 3747, "Jenga": 2741, "vegetables": 686, "boxes": 1152, "grasping": 3725, "gazes": 2097, "visiting": 2431, "seated": 429, "sundress": 2841, "other": 67, "participant": 4776, "t-shirt": 202, "turbans": 4994, "dots": 3245, "thing": 3467, "tribal": 2628, "bartender": 2601, "containing": 2192, "winning": 3459, "schoolgirls": 4405, "white": 20, "shelter": 2982, "strap": 3333, "BMW": 4888, "obstacle": 947, "surroundings": 3524, "parents": 1658, "pillar": 2108, "lecture": 1989, "ducks": 2102, "waterfall": 1051, "blond": 167, "headband": 1303, "steam": 3176, "alike": 3726, "skier": 662, "dreads": 4705, "ballet": 1484, "sleeps": 994, "navy": 1077, "sets": 1286, "saluting": 4327, "windows": 867, "milling": 3471, "lining": 2482, "donuts": 4560, "speeding": 3045, "texts": 4804, "pro": 4393, "doctor": 1641, "park": 126, "citizens": 3250, "quiet": 2931, "skyline": 2360, "bowling": 555, "item": 1409, "full": 336, "if": 1479, "punk": 4034, "employees": 2591, "acrobatic": 3334, "them": 147, "butt": 4370, "fruits": 1495, "California": 4094, "intently": 1429, "buffet": 2533, "walls": 1055, "dig": 2224, "figures": 2127, "eastern": 1908, "flowery": 3476, "interact": 2911, "guitarist": 1125, "25": 4996, "juggles": 2699, "Multiple": 1868, "presenting": 2587, "sleeve": 3082, "police": 484, "mannequin": 2323, "rollerskates": 1990, "workbench": 4243, "crosswalk": 940, "scooping": 4572, "kabobs": 4933, "unit": 4304, "Italian": 4311, "main": 2619, "sips": 4162, "Welcome": 4795, "sad": 2177, "steel": 1651, "pulley": 4079, "glancing": 4510, "halter": 3346, "cool": 2107}